gh_comment_reader/__init__.py
gh_comment_reader/cli.py
gh_comment_reader/comments.py
gh_comment_reader/display.py
gh_comment_reader/main.py
gh_comment_reader/models.py
gh_comment_reader/pr_comments.gql
gh_comment_reader-0.1.6.dist-info/WHEEL
gh_comment_reader-0.1.6.dist-info/entry_points.txt
gh_comment_reader-0.1.6.dist-info/METADATA
gh_comment_reader-0.1.6.dist-info/RECORD
