Metadata-Version: 2.4
Name: gh-comment-reader
Version: 0.1.6
Summary: GitHub Comment Reader - CLI tool for easily reading GitHub PR comments
Author: Andrew Northall
Author-email: Andrew Northall <andrew@northall.me.uk>
License-Expression: MIT
Requires-Dist: pydantic>=2.11.7
Requires-Dist: typer>=0.17.3
Requires-Dist: rich>=13.0.0
Requires-Dist: gql[aiohttp]>=4.0.0
Requires-Dist: requests>=2.32.5
Requires-Python: >=3.13
